fuzzysorteddict.py
fuzzysorteddict-1.1.0.dist-info/LICENSE
fuzzysorteddict-1.1.0.dist-info/WHEEL
fuzzysorteddict-1.1.0.dist-info/METADATA
fuzzysorteddict-1.1.0.dist-info/RECORD
