Metadata-Version: 2.1
Name: fuzzysorteddict
Version: 1.1.0
Summary: A sorted dictionary with nearest-key lookup
Home-page: https://github.com/ncsuarc/FuzzySortedDict
Keywords: dictionary
Author: NC State Aerial Robotics Club
Author-email: aerialrobotics@ncsu.edu
Requires-Python: >=3.5
Classifier: Programming Language :: Python :: 3
Classifier: Programming Language :: Python :: 3.5
Classifier: Programming Language :: Python :: 3.6
Classifier: Programming Language :: Python :: 3.7
Classifier: Programming Language :: Python :: 3.8
Requires-Dist: sortedcontainers (>=2.1.0,<3.0.0)
